requisites/__init__.py
requisites/version.py
python_requisites-0.1.0.dist-info/LICENSE
python_requisites-0.1.0.dist-info/METADATA
python_requisites-0.1.0.dist-info/WHEEL
python_requisites-0.1.0.dist-info/RECORD
