Metadata-Version: 2.1
Name: python-requisites
Version: 0.1.0
Summary: Python Requisites: A dynamic tool for the explicit declaration and analysis of dependencies in Python objects, streamlining the process of identifying and managing required elements in your code.
License: Apache-2.0
Author: Allen Chou
Author-email: f1470891079@gmail.com
Requires-Python: >=3.7,<4.0
Classifier: License :: OSI Approved :: Apache Software License
Classifier: Programming Language :: Python :: 3
Classifier: Programming Language :: Python :: 3.7
Classifier: Programming Language :: Python :: 3.8
Classifier: Programming Language :: Python :: 3.9
Classifier: Programming Language :: Python :: 3.10
Classifier: Programming Language :: Python :: 3.11
Classifier: Programming Language :: Python :: 3.12
Requires-Dist: typing-extensions (>=4,<5)
